{
    "errors": [],
    "orig": {
        "aktenzeichen": "hrb 503945",
        "amtsgericht": "jena",
        "federal_state": "th",
        "full_text": "amtsgericht jena aktenzeichen: hrb 503945 \nbekannt gemacht am: 21.06.2017 21:00 uhr\n\n\n\n\ndie in () gesetzten angaben der geschäftsanschrift und des unternehmensgegenstandes erfolgen ohne gewähr.\nveränderungen\n21.06.2017\n\nhrb 503945: biotransforming gmbh, nordhausen, wehrstraße 1, 99734 nordhausen. die gesellschaft wird durch den/die liquidator/en vertreten. geändert, nun: liquidator: stein, harry, nordhausen ot sundhausen, *07.11.1950. die gesellschaft ist durch rechtskräftige abweisung eines antrags auf eröffnung des insolvenzverfahrens mangels masse aufgelöst (az. in 6/17 amtsgericht mühlhausen). von amts wegen eingetragen.",
        "notice_id": "105733",
        "posted_on": "2017-06-21",
        "url": "https://www.handelsregisterbekanntmachungen.de/en/skripte/hrb.php?rb_id=105733&land_abk=th"
    },
    "parsed": {}
}