{
    "errors": [],
    "orig": {
        "aktenzeichen": "HRB 37641",
        "amtsgericht": "Düsseldorf",
        "federal_state": "nw",
        "full_text": "Amtsgericht Düsseldorf Aktenzeichen: HRB 37641 \nBekannt gemacht am: 01.03.2005 08:56 Uhr\n\n\n\n\nDie in () gesetzten Angaben der Geschäftsanschrift und des Geschäftszweiges erfolgen ohne Gewähr.\nVeränderungen\n25.02.2005\n\nADD-Feinkost GmbH, Düsseldorf (Schuhmannstraße 44, 40237 Düsseldorf). Die Gesellschaft ist aufgelöst. Nunmehr bestellt als Liquidator: Glogic-Albinovic, Dzemila, geb. Nuhovic, Düsseldorf, *28.04.1950, einzelvertretungsberechtigt mit der Befugnis im Namen der Gesellschaft mit sich im eigenen Namen oder als Vertreter eines Dritten Rechtsgeschäfte abzuschließen.",
        "notice_id": "15984",
        "posted_on": "2005-03-01",
        "url": "https://www.handelsregisterbekanntmachungen.de/en/skripte/hrb.php?rb_id=15984&land_abk=nw"
    },
    "parsed": {
        "flags": [
            {
                "flag": "ignore_for_now",
                "text": "Die Gesellschaft ist aufgelöst ."
            }
        ]
    }
}