{
    "errors": [],
    "orig": {
        "aktenzeichen": "hrb 1931",
        "amtsgericht": "osnabrück",
        "federal_state": "ni",
        "full_text": "amtsgericht osnabrück aktenzeichen: hrb 1931 \nbekannt gemacht am: 22.06.2017 19:00 uhr\n\n\n\n\nin () gesetzte angaben der anschrift und des geschäftszweiges erfolgen ohne gewähr:\nveränderungen\n22.06.2017\n\nhrb 1931: elektro-bau-montage verwaltungsgesellschaft mit beschränkter haftung, osnabrück, karmannstraße 13, 49084 osnabrück. die gesellschafterversammlung vom 24.01.2017 hat die neufassung der satzung und damit die änderung der firma sowie der allgemeinen vertretungsregeglung beschlossen. die weitere gesellschafterversammlung vom 24.04.2017 hat eine änderung des gesellschaftsvertrages in § 6 (gesellschafterversammlung) beschlossen. geändert, nun: neue firma: ebm elektro-bau-montage verwaltungs gmbh. ist nur ein geschäftsführer bestellt, so vertritt er die gesellschaft allein. sind mehrere geschäftsführer bestellt, so wird die gesellschaft durch zwei geschäftsführer oder durch einen geschäftsführer gemeinsam mit einem prokuristen vertreten.",
        "notice_id": "441211",
        "posted_on": "2017-06-22",
        "url": "https://www.handelsregisterbekanntmachungen.de/en/skripte/hrb.php?rb_id=441211&land_abk=ni"
    },
    "parsed": {}
}