{
    "errors": [],
    "orig": {
        "aktenzeichen": "HRB 8124",
        "amtsgericht": "Landshut",
        "federal_state": "by",
        "full_text": "Amtsgericht Landshut Aktenzeichen: HRB 8124   \nBekannt gemacht am: 31.10.2011 12:00 Uhr\n\n\n\n\nIn ( ) gesetzte Angaben der Anschrift und des Geschäftszweiges erfolgen ohne Gewähr.\nVeränderungen\n27.10.2011\n\nSinnProjekt UG (haftungsbeschränkt), Landshut, Am Mitterfeld 43, 84028 Landshut. Neuer Sitz: Geesthacht. Geschäftsanschrift: Koopskamp 15 b, 21502 Geesthacht. Sitz verlegt nach Geesthacht (nun Amtsgericht Lübeck, HRB 11530 HL).",
        "notice_id": "546303",
        "posted_on": "2011-10-31",
        "url": "https://www.handelsregisterbekanntmachungen.de/en/skripte/hrb.php?rb_id=546303&land_abk=by"
    },
    "parsed": {
        "labels": [
            {
                "label": "address",
                "text": " Koopskamp 15 b , 21502 Geesthacht ."
            }
        ]
    }
}