{
    "orig": {
        "aktenzeichen": "HRB 9367",
        "amtsgericht": "Duisburg",
        "federal_state": "nw",
        "full_text": "Amtsgericht Duisburg Aktenzeichen: HRB 9367 \nBekannt gemacht am: 17.12.2010 12:00 Uhr\n\n\n\n\nIn () gesetzte Angaben der Anschrift und des Geschäftszweiges erfolgen ohne Gewähr.\nVeränderungen\n10.12.2010\n\nBarbara Witz Häusliche Krankenpflege GmbH, Duisburg, Gerhart-Hauptmann-Str. 10, 47058 Duisburg. Änderung zur Geschäftsanschrift: Gerhart-Hauptmann-Str. 10, 47058 Duisburg.",
        "notice_id": "621786",
        "posted_on": "2010-12-17",
        "url": "https://www.handelsregisterbekanntmachungen.de/en/skripte/hrb.php?rb_id=621786&land_abk=nw"
    },
    "parsed": [
        {
            "label": "address",
            "text": " Gerhart - Hauptmann - Str ."
        }
    ]
}