{
    "errors": [],
    "orig": {
        "aktenzeichen": "hrb 20801",
        "amtsgericht": "stendal",
        "federal_state": "st",
        "full_text": "amtsgericht stendal aktenzeichen: hrb 20801 \nbekannt gemacht am: 25.11.2016 10:48 uhr\n\n\n\n\ndie in () gesetzten angaben der geschäftsanschrift und des geschäftszweiges erfolgen ohne gewähr.\nveränderungen\n25.11.2016\n\nhrb 20801: biolounge gmbh, magdeburg, blankenburger straße 10/12, 39118 magdeburg. geändert, nun: geschäftsanschrift: cracauer str. 66, 39114 magdeburg.",
        "notice_id": "96579",
        "posted_on": "2016-11-25",
        "url": "https://www.handelsregisterbekanntmachungen.de/en/skripte/hrb.php?rb_id=96579&land_abk=st"
    },
    "parsed": {}
}